{
	"data": [
    {
      "idno": 33196174,
      "customerReference": 1553194,
      "documentNumber": 27000065,
      "beneficaryAccountNumber": "32396389086",
      "beneficaryBankName": "STATE BANK OF INDIA",
      "beneficaryBranchName": "MUMBAI",
      "beneficaryName": "AFSANA SULTANA",
      "beneficaryCorespondingBankName": "SBI",
      "documentDate": 1515542400000,
      "documentFinanceYear": 2017,
      "foreignCurrencyCode": "004",
      "foreignTransactionAmount": 600000000000000034.115,
      "currencyQuoteName": "INR",
      "serviceDescription": "EFT",
      "transactionStatusDesc": null,
      "transactionTypeDesc": "REMITTANCE",
      "collectionDocumentNo": 27000064,
      "collectionDocumentCode": 2,
      "collectionDocumentFinYear": 2017,
      "branchDesc": "ONLINE",
      "trnxIdNumber": "2017/27000065",
      "customerId": 5218,
      "applicationCountryId": null,
      "companyId": null,
      "currencyId": null,
      "languageId": null,
      "beneficiaryRelationSeqId": 88041,
      "localTrnxAmount": 3,
      "sourceOfIncomeId": 1,
      "purposeOfTrnx": null
    },
    {
      "idno": 33196177,
      "customerReference": 1553194,
      "documentNumber": 27000068,
      "beneficaryAccountNumber": "11297591218",
      "beneficaryBankName": "STATE BANK OF INDIA",
      "beneficaryBranchName": "JAGATSINGHPUR ADB",
      "beneficaryName": "UDDIN RABIL MIR",
      "beneficaryCorespondingBankName": "SBI",
      "documentDate": 1515542400000,
      "documentFinanceYear": 2017,
      "foreignCurrencyCode": "004",
      "foreignTransactionAmount": 4121.75,
      "currencyQuoteName": "INR",
      "serviceDescription": "EFT",
      "transactionStatusDesc": null,
      "transactionTypeDesc": "REMITTANCE",
      "collectionDocumentNo": 27000067,
      "collectionDocumentCode": 2,
      "collectionDocumentFinYear": 2017,
      "branchDesc": "ONLINE",
      "trnxIdNumber": "2017/27000068",
      "customerId": 5218,
      "applicationCountryId": null,
      "companyId": null,
      "currencyId": null,
      "languageId": null,
      "beneficiaryRelationSeqId": 1439,
      "localTrnxAmount": 19.5,
      "sourceOfIncomeId": 1,
      "purposeOfTrnx": null
    },
    {
      "idno": 33196178,
      "customerReference": 1553194,
      "documentNumber": 27000069,
      "beneficaryAccountNumber": "11297591218",
      "beneficaryBankName": "STATE BANK OF INDIA",
      "beneficaryBranchName": "JAGATSINGHPUR ADB",
      "beneficaryName": "UDDIN RABIL MIR",
      "beneficaryCorespondingBankName": "SBI",
      "documentDate": 1515542400000,
      "documentFinanceYear": 2017,
      "foreignCurrencyCode": "004",
      "foreignTransactionAmount": 4121.75,
      "currencyQuoteName": "INR",
      "serviceDescription": "EFT",
      "transactionStatusDesc": null,
      "transactionTypeDesc": "REMITTANCE",
      "collectionDocumentNo": 27000068,
      "collectionDocumentCode": 2,
      "collectionDocumentFinYear": 2017,
      "branchDesc": "ONLINE",
      "trnxIdNumber": "2017/27000069",
      "customerId": 5218,
      "applicationCountryId": null,
      "companyId": null,
      "currencyId": null,
      "languageId": null,
      "beneficiaryRelationSeqId": 1439,
      "localTrnxAmount": 19.5,
      "sourceOfIncomeId": 1,
      "purposeOfTrnx": null
    },
    {
      "idno": 33196176,
      "customerReference": 1553194,
      "documentNumber": 27000067,
      "beneficaryAccountNumber": "32396389086",
      "beneficaryBankName": "STATE BANK OF INDIA",
      "beneficaryBranchName": "MUMBAI",
      "beneficaryName": "AFSANA SULTANA",
      "beneficaryCorespondingBankName": "SBI",
      "documentDate": 1515542400000,
      "documentFinanceYear": 2017,
      "foreignCurrencyCode": "004",
      "foreignTransactionAmount": 490.594,
      "currencyQuoteName": "INR",
      "serviceDescription": "EFT",
      "transactionStatusDesc": null,
      "transactionTypeDesc": "REMITTANCE",
      "collectionDocumentNo": 27000066,
      "collectionDocumentCode": 2,
      "collectionDocumentFinYear": 2017,
      "branchDesc": "ONLINE",
      "trnxIdNumber": "2017/27000067",
      "customerId": 5218,
      "applicationCountryId": null,
      "companyId": null,
      "currencyId": null,
      "languageId": null,
      "beneficiaryRelationSeqId": 88041,
      "localTrnxAmount": 2.321,
      "sourceOfIncomeId": 1,
      "purposeOfTrnx": null
    },
    {
      "idno": 33196179,
      "customerReference": 1553194,
      "documentNumber": 27000070,
      "beneficaryAccountNumber": "11297591218",
      "beneficaryBankName": "STATE BANK OF INDIA",
      "beneficaryBranchName": "JAGATSINGHPUR ADB",
      "beneficaryName": "UDDIN RABIL MIR",
      "beneficaryCorespondingBankName": "SBI",
      "documentDate": 1515542400000,
      "documentFinanceYear": 2017,
      "foreignCurrencyCode": "004",
      "foreignTransactionAmount": 4121.75,
      "currencyQuoteName": "INR",
      "serviceDescription": "EFT",
      "transactionStatusDesc": null,
      "transactionTypeDesc": "REMITTANCE",
      "collectionDocumentNo": 27000069,
      "collectionDocumentCode": 2,
      "collectionDocumentFinYear": 2017,
      "branchDesc": "ONLINE",
      "trnxIdNumber": "2017/27000070",
      "customerId": 5218,
      "applicationCountryId": null,
      "companyId": null,
      "currencyId": null,
      "languageId": null,
      "beneficiaryRelationSeqId": 1439,
      "localTrnxAmount": 19.5,
      "sourceOfIncomeId": 1,
      "purposeOfTrnx": null
    },
    {
      "idno": 33196180,
      "customerReference": 1553194,
      "documentNumber": 27000071,
      "beneficaryAccountNumber": "11297591218",
      "beneficaryBankName": "STATE BANK OF INDIA",
      "beneficaryBranchName": "JAGATSINGHPUR ADB",
      "beneficaryName": "UDDIN RABIL MIR",
      "beneficaryCorespondingBankName": "SBI",
      "documentDate": 1515542400000,
      "documentFinanceYear": 2017,
      "foreignCurrencyCode": "004",
      "foreignTransactionAmount": 4121.75,
      "currencyQuoteName": "INR",
      "serviceDescription": "EFT",
      "transactionStatusDesc": null,
      "transactionTypeDesc": "REMITTANCE",
      "collectionDocumentNo": 27000070,
      "collectionDocumentCode": 2,
      "collectionDocumentFinYear": 2017,
      "branchDesc": "ONLINE",
      "trnxIdNumber": "2017/27000071",
      "customerId": 5218,
      "applicationCountryId": null,
      "companyId": null,
      "currencyId": null,
      "languageId": null,
      "beneficiaryRelationSeqId": 1439,
      "localTrnxAmount": 19.5,
      "sourceOfIncomeId": 1,
      "purposeOfTrnx": null
    },
    {
      "idno": 33196181,
      "customerReference": 1553194,
      "documentNumber": 27000072,
      "beneficaryAccountNumber": "11297591218",
      "beneficaryBankName": "STATE BANK OF INDIA",
      "beneficaryBranchName": "JAGATSINGHPUR ADB",
      "beneficaryName": "UDDIN RABIL MIR",
      "beneficaryCorespondingBankName": "SBI",
      "documentDate": 1515542400000,
      "documentFinanceYear": 2017,
      "foreignCurrencyCode": "004",
      "foreignTransactionAmount": 518.495,
      "currencyQuoteName": "INR",
      "serviceDescription": "EFT",
      "transactionStatusDesc": null,
      "transactionTypeDesc": "REMITTANCE",
      "collectionDocumentNo": 27000071,
      "collectionDocumentCode": 2,
      "collectionDocumentFinYear": 2017,
      "branchDesc": "ONLINE",
      "trnxIdNumber": "2017/27000072",
      "customerId": 5218,
      "applicationCountryId": null,
      "companyId": null,
      "currencyId": null,
      "languageId": null,
      "beneficiaryRelationSeqId": 1439,
      "localTrnxAmount": 2.453,
      "sourceOfIncomeId": 1,
      "purposeOfTrnx": null
    },
    {
      "idno": 33196182,
      "customerReference": 1553194,
      "documentNumber": 27000073,
      "beneficaryAccountNumber": "11297591218",
      "beneficaryBankName": "STATE BANK OF INDIA",
      "beneficaryBranchName": "JAGATSINGHPUR ADB",
      "beneficaryName": "UDDIN RABIL MIR",
      "beneficaryCorespondingBankName": "SBI",
      "documentDate": 1515542400000,
      "documentFinanceYear": 2017,
      "foreignCurrencyCode": "004",
      "foreignTransactionAmount": 507.292,
      "currencyQuoteName": "INR",
      "serviceDescription": "EFT",
      "transactionStatusDesc": null,
      "transactionTypeDesc": "REMITTANCE",
      "collectionDocumentNo": 27000072,
      "collectionDocumentCode": 2,
      "collectionDocumentFinYear": 2017,
      "branchDesc": "ONLINE",
      "trnxIdNumber": "2017/27000073",
      "customerId": 5218,
      "applicationCountryId": null,
      "companyId": null,
      "currencyId": null,
      "languageId": null,
      "beneficiaryRelationSeqId": 1439,
      "localTrnxAmount": 2.4,
      "sourceOfIncomeId": 1,
      "purposeOfTrnx": null
    },
    {
      "idno": 33196183,
      "customerReference": 1553194,
      "documentNumber": 27000074,
      "beneficaryAccountNumber": "11297591218",
      "beneficaryBankName": "STATE BANK OF INDIA",
      "beneficaryBranchName": "JAGATSINGHPUR ADB",
      "beneficaryName": "UDDIN RABIL MIR",
      "beneficaryCorespondingBankName": "SBI",
      "documentDate": 1515542400000,
      "documentFinanceYear": 2017,
      "foreignCurrencyCode": "004",
      "foreignTransactionAmount": 4121.75,
      "currencyQuoteName": "INR",
      "serviceDescription": "EFT",
      "transactionStatusDesc": null,
      "transactionTypeDesc": "REMITTANCE",
      "collectionDocumentNo": 27000073,
      "collectionDocumentCode": 2,
      "collectionDocumentFinYear": 2017,
      "branchDesc": "ONLINE",
      "trnxIdNumber": "2017/27000074",
      "customerId": 5218,
      "applicationCountryId": null,
      "companyId": null,
      "currencyId": null,
      "languageId": null,
      "beneficiaryRelationSeqId": 1439,
      "localTrnxAmount": 19.5,
      "sourceOfIncomeId": 1,
      "purposeOfTrnx": null
    },
    {
      "idno": 33196184,
      "customerReference": 1553194,
      "documentNumber": 27000075,
      "beneficaryAccountNumber": "32396389086",
      "beneficaryBankName": "STATE BANK OF INDIA",
      "beneficaryBranchName": "MUMBAI",
      "beneficaryName": "AFSANA SULTANA",
      "beneficaryCorespondingBankName": "SBI",
      "documentDate": 1515542400000,
      "documentFinanceYear": 2017,
      "foreignCurrencyCode": "004",
      "foreignTransactionAmount": 490.594,
      "currencyQuoteName": "INR",
      "serviceDescription": "EFT",
      "transactionStatusDesc": null,
      "transactionTypeDesc": "REMITTANCE",
      "collectionDocumentNo": 27000074,
      "collectionDocumentCode": 2,
      "collectionDocumentFinYear": 2017,
      "branchDesc": "ONLINE",
      "trnxIdNumber": "2017/27000075",
      "customerId": 5218,
      "applicationCountryId": null,
      "companyId": null,
      "currencyId": null,
      "languageId": null,
      "beneficiaryRelationSeqId": 88041,
      "localTrnxAmount": 2.321,
      "sourceOfIncomeId": 1,
      "purposeOfTrnx": null
    },
    {
      "idno": 33196185,
      "customerReference": 1553194,
      "documentNumber": 27000076,
      "beneficaryAccountNumber": "11297591218",
      "beneficaryBankName": "STATE BANK OF INDIA",
      "beneficaryBranchName": "JAGATSINGHPUR ADB",
      "beneficaryName": "UDDIN RABIL MIR",
      "beneficaryCorespondingBankName": "SBI",
      "documentDate": 1515542400000,
      "documentFinanceYear": 2017,
      "foreignCurrencyCode": "004",
      "foreignTransactionAmount": 507.292,
      "currencyQuoteName": "INR",
      "serviceDescription": "EFT",
      "transactionStatusDesc": null,
      "transactionTypeDesc": "REMITTANCE",
      "collectionDocumentNo": 27000075,
      "collectionDocumentCode": 2,
      "collectionDocumentFinYear": 2017,
      "branchDesc": "ONLINE",
      "trnxIdNumber": "2017/27000076",
      "customerId": 5218,
      "applicationCountryId": null,
      "companyId": null,
      "currencyId": null,
      "languageId": null,
      "beneficiaryRelationSeqId": 1439,
      "localTrnxAmount": 2.4,
      "sourceOfIncomeId": 1,
      "purposeOfTrnx": null
    },
    {
      "idno": 33196186,
      "customerReference": 1553194,
      "documentNumber": 27000077,
      "beneficaryAccountNumber": "11297591218",
      "beneficaryBankName": "STATE BANK OF INDIA",
      "beneficaryBranchName": "JAGATSINGHPUR ADB",
      "beneficaryName": "UDDIN RABIL MIR",
      "beneficaryCorespondingBankName": "SBI",
      "documentDate": 1515542400000,
      "documentFinanceYear": 2017,
      "foreignCurrencyCode": "004",
      "foreignTransactionAmount": 4121.75,
      "currencyQuoteName": "INR",
      "serviceDescription": "EFT",
      "transactionStatusDesc": null,
      "transactionTypeDesc": "REMITTANCE",
      "collectionDocumentNo": 27000076,
      "collectionDocumentCode": 2,
      "collectionDocumentFinYear": 2017,
      "branchDesc": "ONLINE",
      "trnxIdNumber": "2017/27000077",
      "customerId": 5218,
      "applicationCountryId": null,
      "companyId": null,
      "currencyId": null,
      "languageId": null,
      "beneficiaryRelationSeqId": 1439,
      "localTrnxAmount": 19.5,
      "sourceOfIncomeId": 1,
      "purposeOfTrnx": null
    },
    {
      "idno": 33196187,
      "customerReference": 1553194,
      "documentNumber": 27000078,
      "beneficaryAccountNumber": "32396389086",
      "beneficaryBankName": "STATE BANK OF INDIA",
      "beneficaryBranchName": "MUMBAI",
      "beneficaryName": "AFSANA SULTANA",
      "beneficaryCorespondingBankName": "SBI",
      "documentDate": 1515542400000,
      "documentFinanceYear": 2017,
      "foreignCurrencyCode": "004",
      "foreignTransactionAmount": 490.594,
      "currencyQuoteName": "INR",
      "serviceDescription": "EFT",
      "transactionStatusDesc": null,
      "transactionTypeDesc": "REMITTANCE",
      "collectionDocumentNo": 27000077,
      "collectionDocumentCode": 2,
      "collectionDocumentFinYear": 2017,
      "branchDesc": "ONLINE",
      "trnxIdNumber": "2017/27000078",
      "customerId": 5218,
      "applicationCountryId": null,
      "companyId": null,
      "currencyId": null,
      "languageId": null,
      "beneficiaryRelationSeqId": 88041,
      "localTrnxAmount": 2.321,
      "sourceOfIncomeId": 1,
      "purposeOfTrnx": null
    },
    {
      "idno": 33196202,
      "customerReference": 1553194,
      "documentNumber": 27000093,
      "beneficaryAccountNumber": "32396389086",
      "beneficaryBankName": "STATE BANK OF INDIA",
      "beneficaryBranchName": "MUMBAI",
      "beneficaryName": "AFSANA SULTANA",
      "beneficaryCorespondingBankName": "SBI",
      "documentDate": 1515715200000,
      "documentFinanceYear": 2017,
      "foreignCurrencyCode": "004",
      "foreignTransactionAmount": 490.594,
      "currencyQuoteName": "INR",
      "serviceDescription": "EFT",
      "transactionStatusDesc": null,
      "transactionTypeDesc": "REMITTANCE",
      "collectionDocumentNo": 27000092,
      "collectionDocumentCode": 2,
      "collectionDocumentFinYear": 2017,
      "branchDesc": "ONLINE",
      "trnxIdNumber": "2017/27000093",
      "customerId": 5218,
      "applicationCountryId": null,
      "companyId": null,
      "currencyId": null,
      "languageId": null,
      "beneficiaryRelationSeqId": 88041,
      "localTrnxAmount": 2.321,
      "sourceOfIncomeId": 1,
      "purposeOfTrnx": null
    }
  ]
}